README.md
csup.py
setup.py
csup.egg-info/PKG-INFO
csup.egg-info/SOURCES.txt
csup.egg-info/dependency_links.txt
csup.egg-info/entry_points.txt
csup.egg-info/requires.txt
csup.egg-info/top_level.txt