Metadata-Version: 1.1
Name: csup
Version: 1.0
Summary: Container Security UPloading and reporting tool (CSUP)
Home-page: UNKNOWN
Author: Steven McGrath <smcgrath@tenable.com>
Author-email: smcgrath@tenable.com
License: MIT
Keywords: development docker security
Platform: UNKNOWN
Classifier: Development Status :: 3 - Alpha
Classifier: Intended Audience :: Developers
Classifier: Topic :: Software Development :: Build Tools
Classifier: License :: OSI Approved :: MIT License
Classifier: Programming Language :: Python :: 2.7
Classifier: Programming Language :: Python :: 3
Classifier: Programming Language :: Python :: 3.3
